fastgcf/__init__.py
fastgcf/_converters.py
fastgcf/_handler.py
fastgcf/_proxy.py
fastgcf/_router.py
fastgcf/_streams.py
fastgcf/_transport.py
fastgcf-1.1.0.dist-info/licenses/LICENCE
fastgcf-1.1.0.dist-info/METADATA
fastgcf-1.1.0.dist-info/WHEEL
fastgcf-1.1.0.dist-info/top_level.txt
fastgcf-1.1.0.dist-info/RECORD
