Metadata-Version: 2.4
Name: fastgcf
Version: 1.1.0
Summary: FastAPI in Google Cloud Functions
Home-page: https://github.com/TigranZalian/fastgcf
Author: Tigran Zalian
Author-email: tigraanzalian@gmail.com
Classifier: Intended Audience :: Developers
Classifier: License :: OSI Approved :: MIT License
Classifier: Programming Language :: Python :: 3
Classifier: Programming Language :: Python :: 3.6
Classifier: Programming Language :: Python :: 3.7
Classifier: Programming Language :: Python :: 3.8
Classifier: Programming Language :: Python :: 3.9
Classifier: Programming Language :: Python :: 3.10
Classifier: Programming Language :: Python :: 3.11
License-File: LICENCE
Requires-Dist: functions-framework
Requires-Dist: fastapi==0.116.1
Requires-Dist: httpx==0.27.0
Requires-Dist: nest_asyncio==1.5.8
Dynamic: author
Dynamic: author-email
Dynamic: classifier
Dynamic: description
Dynamic: description-content-type
Dynamic: home-page
Dynamic: license-file
Dynamic: requires-dist
Dynamic: summary
